{
  "_note": "STORY = comportamento dell'avventura fantasy, 100% dati (stesso interprete del pack martina). 'fontana' e 'bacheca' sono sorprese semplici (nessuna scena); 'pergamena' resta quella 'finale' che, visitata per ultima dopo le altre due, apre il Decreto Reale. 'contratto' resta il nome tecnico della scena (coerente con lo schema CONFIG). CONFIG.ballo esiste solo perché lo schema lo richiede: nessuna scena lo usa più.",

  "eventi": [
    { "id": "fontana", "quando": "interagisci:fontana",
      "fai": [ { "sorpresa": "fontana" } ] },

    { "id": "bacheca", "quando": "interagisci:bacheca",
      "fai": [ { "sorpresa": "bacheca" } ] },

    { "id": "pergamena", "quando": "interagisci:pergamena",
      "se": { "all": ["!trovato.pergamena", "trovato.fontana", "trovato.bacheca", "!fatto.contratto"] },
      "fai": [ { "set": "trovato.pergamena" }, { "scena": "contratto" } ],
      "altrimenti": [ { "sorpresa": "pergamena" } ] },

    { "id": "finn", "quando": "interagisci:npc",
      "fai": [ { "set": "npcParlato" }, { "dialogo": "finn" } ] },

    { "id": "gatto", "quando": "interagisci:gatto",
      "fai": [
        { "sveglia": "gatto" }, { "verso": "gatto" }, { "sfx": "meow" },
        { "se": "!segreto.gatto", "fai": [ { "set": "segreto.gatto" }, { "vibra": 40 } ] },
        { "se": { "all": ["prima_interazione", "!fatto.fusa"] },
          "fai": [ { "set": "fatto.fusa" }, { "scena": "fusa" }, { "dialogo": "gatto" } ],
          "altrimenti": [ { "dialogo": "gatto" } ] } ] },

    { "id": "finestra", "quando": "interagisci:finestra",
      "fai": [ { "set": "segreto.finestra" },
               { "popup": { "img": "@pop_cielo", "testo": "$finestra.testo", "verso": [50, 14] } } ] }
  ],

  "scene": {
    "contratto": { "passi": [
      { "inizio": true },
      { "set": "fatto.contratto" },
      { "suggerimento": false },
      { "nero": true },
      { "scrivi": { "testo": "$contratto.intro", "pausa": 1.4 } },
      { "documento": true },
      { "fine": true } ] },

    "fusa": { "passi": [
      { "inizio": true },
      { "statoGiocatore": "interact" },
      { "cuori": { "su": "gatto", "n": 14 } },
      { "attesa": 0.38 },
      { "cuori": { "su": "gatto", "n": 8 } },
      { "attesa": 0.57 },
      { "fine": true } ] }
  },

  "dialoghi": {
    "finn":  { "nome": "$nomi.lui", "modo": "sacchetto", "fonte": "$dialoghi",
               "emotivo": true, "verso": "npc" },
    "gatto": { "nome": "$gatto.nome", "righe": ["$gatto.messaggio"],
               "ritratto": "@pt_gatto", "verso": "gatto" }
  },

  "segreti": [
    { "id": "gatto",     "flag": "segreto.gatto", "hud": "🐾" },
    { "id": "finestra",  "flag": "segreto.finestra" },
    { "id": "contratto", "flag": "fatto.contratto" }
  ],

  "finali": [
    { "id": "principale", "se": "trovato.*",
      "titolo": "$finale.titolo", "testo": "$finale.testo" }
  ],

  "ui": {
    "giorni": "INSIEME IN QUESTO REGNO DA {g} GIORNI ❤",
    "segretiCompleti": "Complimenti!\nHai scoperto tutta la magia nascosta di questo villaggio. ❤️",
    "segretiParziali": "Hai trovato {n}/{tot} segreti del villaggio.\nRicomincia per scoprirli tutti.\n💡 Indizio: prova a cambiare l'ordine in cui esplori i luoghi."
  }
}
